flet_svg/__init__.py
flet_svg/flet_svg.py
flutter/flet_svg/CHANGELOG.md
flutter/flet_svg/LICENSE
flutter/flet_svg/README.md
flutter/flet_svg/pubspec.lock
flutter/flet_svg/pubspec.yaml
flutter/flet_svg/lib/flet_svg.dart
flutter/flet_svg/lib/src/create_control.dart
flutter/flet_svg/lib/src/flet_svg.dart
flet_svg-0.1.0.dist-info/METADATA
flet_svg-0.1.0.dist-info/WHEEL
flet_svg-0.1.0.dist-info/top_level.txt
flet_svg-0.1.0.dist-info/RECORD
