Metadata-Version: 2.4
Name: flet-svg
Version: 0.1.0
Summary: A Flet extension to render SVG with flutter_svg.
Author-email: Atsushi Tatsuma <yoshoku@outlook.com>
License: The MIT License (MIT)
Project-URL: Homepage, https://github.com/yoshoku/flet-svg
Project-URL: Repository, https://github.com/yoshoku/flet-svg
Project-URL: Issues, https://github.com/yoshoku/flet-svg/issues
Requires-Python: >=3.9
Requires-Dist: flet>=0.28.3
